MANIFEST.in
setup.py
sajid_test_file/README.md
sajid_test_file/__init__.py
sajid_test_file/nodes.py
sajid_test_file/pipeline.py
sajid_test_file.egg-info/PKG-INFO
sajid_test_file.egg-info/SOURCES.txt
sajid_test_file.egg-info/dependency_links.txt
sajid_test_file.egg-info/top_level.txt
sajid_test_file/config/parameters/sajid_test_file.yml
tests/__init__.py
tests/test_pipeline.py