Metadata-Version: 2.1
Name: sajid-test-file
Version: 0.1
Summary: Micro-package `sajid_test_file`
